ncbi_refseq_accession_lengths/__init__.py
ncbi_refseq_accession_lengths/db.marisa
ncbi_refseq_accession_lengths/version.py
ncbi_refseq_accession_lengths-2024.9.7.dist-info/METADATA
ncbi_refseq_accession_lengths-2024.9.7.dist-info/WHEEL
ncbi_refseq_accession_lengths-2024.9.7.dist-info/top_level.txt
ncbi_refseq_accession_lengths-2024.9.7.dist-info/RECORD
