Metadata-Version: 2.1
Name: ncbi-refseq-accession-lengths
Version: 2024.9.7
Summary: Taxoniq accession index for NCBI BLAST databases
Home-page: https://github.com/chanzuckerberg/taxoniq
Author: Andrey Kislyuk
Author-email: akislyuk@chanzuckerberg.com
License: MIT License
